psusannx_utils/__init__.py
psusannx_utils/psusannx_utils.py
psusannx_utils-0.0.4.dist-info/METADATA
psusannx_utils-0.0.4.dist-info/WHEEL
psusannx_utils-0.0.4.dist-info/top_level.txt
psusannx_utils-0.0.4.dist-info/RECORD
