Metadata-Version: 2.1
Name: psusannx-utils
Version: 0.0.4
Summary: A package for storing functions that are used across multiple functions & modules in the PSUSANNX project..
Author: Jamie O'Brien
Project-URL: Source Code, https://github.com/jamieob63/psusannx_utils.git
Project-URL: Bug Tracker, https://github.com/jamieob63/psusannx_utils.git/issues
Requires-Dist: pandas (>=1.3.4)
Requires-Dist: beautifulsoup4 (>=4.12.2)
